teyvat/__init__.py
teyvat/albedo/__init__.py
teyvat/albedo/example.py
teyvat-0.0.1.dist-info/METADATA
teyvat-0.0.1.dist-info/WHEEL
teyvat-0.0.1.dist-info/top_level.txt
teyvat-0.0.1.dist-info/RECORD
