Metadata-Version: 2.1
Name: teyvat
Version: 0.0.1
Summary: Everything about Genshin Impact
Home-page: https://github.com/enelepe/teyvat
Author: Enelepe
Author-email: me@enelepe.com
License: UNKNOWN
Project-URL: Bug Tracker, https://github.com/enelepe/teyvat/issues
Platform: UNKNOWN
Classifier: Programming Language :: Python :: 3
Classifier: License :: OSI Approved :: MIT License
Classifier: Operating System :: OS Independent
Requires-Python: >=3.6
